yellhorn_mcp/__init__.py
yellhorn_mcp/cli.py
yellhorn_mcp/server.py
yellhorn_mcp/formatters/__init__.py
yellhorn_mcp/formatters/codebase_snapshot.py
yellhorn_mcp/formatters/context_fetcher.py
yellhorn_mcp/formatters/prompt_formatter.py
yellhorn_mcp/integrations/github_integration.py
yellhorn_mcp/llm/__init__.py
yellhorn_mcp/llm/base.py
yellhorn_mcp/llm/chunking.py
yellhorn_mcp/llm/config.py
yellhorn_mcp/llm/errors.py
yellhorn_mcp/llm/manager.py
yellhorn_mcp/llm/model_families.py
yellhorn_mcp/llm/retry.py
yellhorn_mcp/llm/usage.py
yellhorn_mcp/llm/clients/__init__.py
yellhorn_mcp/llm/clients/gemini_client.py
yellhorn_mcp/llm/clients/openai_client.py
yellhorn_mcp/llm/clients/xai_client.py
yellhorn_mcp/models/metadata_models.py
yellhorn_mcp/processors/__init__.py
yellhorn_mcp/processors/context_processor.py
yellhorn_mcp/processors/judgement_processor.py
yellhorn_mcp/processors/workplan_processor.py
yellhorn_mcp/utils/comment_utils.py
yellhorn_mcp/utils/cost_tracker_utils.py
yellhorn_mcp/utils/git_utils.py
yellhorn_mcp/utils/lsp_utils.py
yellhorn_mcp/utils/search_grounding_utils.py
yellhorn_mcp/utils/token_utils.py
yellhorn_mcp-0.8.1.dist-info/METADATA
yellhorn_mcp-0.8.1.dist-info/WHEEL
yellhorn_mcp-0.8.1.dist-info/entry_points.txt
yellhorn_mcp-0.8.1.dist-info/RECORD
