Metadata-Version: 2.4
Name: yellhorn-mcp
Version: 0.8.1
Summary: Yellhorn offers MCP tools to generate detailed workplans with Gemini 2.5 Pro or OpenAI models and to review diffs against them using your entire codebase as context. Features unified LLM management, automatic chunking, and robust retry logic.
Author: Author
Classifier: License :: OSI Approved :: MIT License
Classifier: Operating System :: OS Independent
Classifier: Programming Language :: Python :: 3
Classifier: Programming Language :: Python :: 3.10
Requires-Python: >=3.10
Requires-Dist: aiohttp~=3.12.13
Requires-Dist: google-api-core~=2.25.1
Requires-Dist: google-genai~=1.38.0
Requires-Dist: jedi~=0.19.2
Requires-Dist: mcp[cli]~=1.14.1
Requires-Dist: openai~=1.108.1
Requires-Dist: pydantic~=2.11.7
Requires-Dist: tenacity<9.0.0
Requires-Dist: tiktoken~=0.11.0
Requires-Dist: xai-sdk~=1.2.0
